{"cameraMode":{"drawMode":0,"name":"Shaded","section":"Shading Mode"},"sceneLighting":true,"audioPlay":false,"sceneViewState":{"m_AlwaysRefresh":false,"showFog":true,"showSkybox":true,"showFlares":true,"showImageEffects":true,"showParticleSystems":true,"showVisualEffectGraphs":true,"m_FxEnabled":true},"in2DMode":false,"pivot":{"x":-7.30974817276001,"y":-2.3993093967437746,"z":27.135326385498048},"rotation":{"x":-0.06476382911205292,"y":-0.013921870850026608,"z":0.0008736642776057124,"w":-0.9978883266448975},"size":34.595890045166019,"orthographic":false}